{"_id":{"$oid":"5e281a1374f9c54bd84c9066"},"global":true,"exists":true,"name":"Python I","description":"Einführung in Grundlagen von Python.","criteria":"Beherschung der Grundlagen von Python (einfache Funktionsausdrücke und Bedingungen)","issuer":{"$oid":"5e28166574f9c54bd84c9048"},"__v":0}
{"_id":{"$oid":"5e281a5974f9c54bd84c9068"},"global":true,"exists":true,"name":"Python II","description":"Erweiterte Grundlagen von Python","criteria":"Beherschung der erweiterten Grundlagen von Python (Klassen und Objekte)","issuer":{"$oid":"5e28166574f9c54bd84c9048"},"__v":0}
{"_id":{"$oid":"5e281ab874f9c54bd84c906a"},"global":true,"exists":true,"name":"Löten I","description":"Grundlagen und sicherer Umgang mit dem Lötkolben.","criteria":"Sichere Bedienung des Lötkolbens und erste praktische Anwendungen.","issuer":{"$oid":"5e28166574f9c54bd84c9048"},"__v":0}
{"_id":{"$oid":"5e281b3e74f9c54bd84c9070"},"global":false,"exists":true,"name":"For-Loop","description":"Erlernen von Schleifen.","criteria":"Erfolgreiche Umsetzung einer Schleife.","issuer":{"$oid":"5e28183674f9c54bd84c9057"},"__v":0}
{"_id":{"$oid":"5e281b6b74f9c54bd84c9075"},"global":false,"exists":true,"name":"IF-Statement","description":"Erlernen einer Bedingung.","criteria":"Erfolgreiche Umsetzung einer Bedingung..","issuer":{"$oid":"5e28183674f9c54bd84c9057"},"__v":0}
{"_id":{"$oid":"5e281cda74f9c54bd84c9085"},"global":false,"exists":true,"name":"Klassen und Objekte","description":"Erlernen der Theorie und Umsetzung von Klassen und Objekten.","criteria":"Instanzen von Klassen und Objekte erstellen.","issuer":{"$oid":"5e2817de74f9c54bd84c9055"},"__v":0}
{"_id":{"$oid":"5e281d2d74f9c54bd84c908a"},"global":false,"exists":true,"name":"Lambda","description":"Nutzen von Lambda-Funktionen.","criteria":"Erfolgreiche Umsetzung von mind. einer Lambda-Funktion.","issuer":{"$oid":"5e2817de74f9c54bd84c9055"},"__v":0}
{"_id":{"$oid":"5e281f5207cdab7de42d5f5b"},"global":false,"exists":true,"name":"Sicherheitseinführung","description":"Einführung in das sorgenfreie Löten.","criteria":"Sicherheitsanweisungen verstehen und befolgen","issuer":{"$oid":"5e28178a74f9c54bd84c9053"},"__v":0}
{"_id":{"$oid":"5e281f9f07cdab7de42d5f60"},"global":false,"exists":true,"name":"Anwendung eines Lötkolben","description":"Bedienung des Lötkolben und erste praktische Erfahrungen.","criteria":"erfolgreiche Bedienung des Lötkolbens","issuer":{"$oid":"5e28178a74f9c54bd84c9053"},"__v":0}
